vanity_ssh_keygen/__main__.py
vanity_ssh_keygen/__version__.py
vanity_ssh_keygen/keygen.py
vanity_ssh_keygen-0.1.0.dist-info/METADATA
vanity_ssh_keygen-0.1.0.dist-info/WHEEL
vanity_ssh_keygen-0.1.0.dist-info/entry_points.txt
vanity_ssh_keygen-0.1.0.dist-info/RECORD
